LICENSE.txt
README.txt
setup.py
src/stxnext/__init__.py
src/stxnext.flashgallery.egg-info/PKG-INFO
src/stxnext.flashgallery.egg-info/SOURCES.txt
src/stxnext.flashgallery.egg-info/dependency_links.txt
src/stxnext.flashgallery.egg-info/namespace_packages.txt
src/stxnext.flashgallery.egg-info/not-zip-safe
src/stxnext.flashgallery.egg-info/requires.txt
src/stxnext.flashgallery.egg-info/top_level.txt
src/stxnext/flashgallery/__init__.py
src/stxnext/flashgallery/config.py
src/stxnext/flashgallery/configure.zcml
src/stxnext/flashgallery/stxnext.flashgallery-configure.zcml
src/stxnext/flashgallery/version.txt
src/stxnext/flashgallery/browser/__init__.py
src/stxnext/flashgallery/browser/autoviewer_config.py
src/stxnext/flashgallery/browser/autoviewer_config.xml.pt
src/stxnext/flashgallery/browser/autoviewer_view.pt
src/stxnext/flashgallery/browser/configure.zcml
src/stxnext/flashgallery/browser/simpleviewer_config.py
src/stxnext/flashgallery/browser/simpleviewer_config.xml.pt
src/stxnext/flashgallery/browser/simpleviewer_view.pt
src/stxnext/flashgallery/browser/simpleviewer_view.py
src/stxnext/flashgallery/profiles/default/jsregistry.xml
src/stxnext/flashgallery/profiles/default/skins.xml
src/stxnext/flashgallery/profiles/default/types/Folder.xml
src/stxnext/flashgallery/skins/flashgallery/autoviewer.swf
src/stxnext/flashgallery/skins/flashgallery/simpleviewer.swf
src/stxnext/flashgallery/skins/flashgallery/swfobject.js