Metadata-Version: 1.0
Name: stxnext.flashgallery
Version: 0.1.0
Summary: Integration of SimpleViewer and AutoViewer photo galleries with Plone.
Home-page: http://stxnext.pl/open-source/stxnext.flashgallery
Author: STX Next Sp. z o.o, Wojciech Lichota
Author-email: info@stxnext.pl, wojciech.lichota@stxnext.pl
License: Zope Public License, Version 2.1 (ZPL)
Keywords: python plone gallery photo flash
Platform: any
Classifier: Development Status :: 3 - Alpha
Classifier: Framework :: Zope2
Classifier: Framework :: Plone
Classifier: Intended Audience :: Developers
Classifier: License :: OSI Approved :: Zope Public License
Classifier: Natural Language :: English
Classifier: Programming Language :: Python
